{
	"name": "practice_credit_scoring",
	"properties": {
		"activities": [
			{
				"name": "application",
				"type": "Copy",
				"dependsOn": [],
				"policy": {
					"timeout": "0.12:00:00",
					"retry": 0,
					"retryIntervalInSeconds": 30,
					"secureOutput": false,
					"secureInput": false
				},
				"userProperties": [],
				"typeProperties": {
					"source": {
						"type": "PostgreSqlV2Source"
					},
					"sink": {
						"type": "DelimitedTextSink",
						"storeSettings": {
							"type": "AzureBlobFSWriteSettings"
						},
						"formatSettings": {
							"type": "DelimitedTextWriteSettings",
							"quoteAllText": true,
							"fileExtension": ".txt"
						}
					},
					"enableStaging": false,
					"translator": {
						"type": "TabularTranslator",
						"typeConversion": true,
						"typeConversionSettings": {
							"allowDataTruncation": true,
							"treatBooleanAsNumber": false
						}
					}
				},
				"inputs": [
					{
						"referenceName": "POSTGRE_loan_modeling",
						"type": "DatasetReference",
						"parameters": {
							"schema_name": "public",
							"table_name": "application"
						}
					}
				],
				"outputs": [
					{
						"referenceName": "CSV_ADLS_faza",
						"type": "DatasetReference",
						"parameters": {
							"container_name": "fazatest",
							"folder_name": "csv_ingestion/loan_modeling",
							"file_name": "application.csv",
							"delimiter_name": ",",
							"row_as_header": true
						}
					}
				]
			},
			{
				"name": "previous_application",
				"type": "Copy",
				"dependsOn": [],
				"policy": {
					"timeout": "0.12:00:00",
					"retry": 0,
					"retryIntervalInSeconds": 30,
					"secureOutput": false,
					"secureInput": false
				},
				"userProperties": [],
				"typeProperties": {
					"source": {
						"type": "PostgreSqlV2Source"
					},
					"sink": {
						"type": "DelimitedTextSink",
						"storeSettings": {
							"type": "AzureBlobFSWriteSettings"
						},
						"formatSettings": {
							"type": "DelimitedTextWriteSettings",
							"quoteAllText": true,
							"fileExtension": ".txt"
						}
					},
					"enableStaging": false,
					"translator": {
						"type": "TabularTranslator",
						"typeConversion": true,
						"typeConversionSettings": {
							"allowDataTruncation": true,
							"treatBooleanAsNumber": false
						}
					}
				},
				"inputs": [
					{
						"referenceName": "POSTGRE_loan_modeling",
						"type": "DatasetReference",
						"parameters": {
							"schema_name": "public",
							"table_name": "previous_application"
						}
					}
				],
				"outputs": [
					{
						"referenceName": "CSV_ADLS_faza",
						"type": "DatasetReference",
						"parameters": {
							"container_name": "fazatest",
							"folder_name": "csv_ingestion/loan_modeling",
							"file_name": "previous_application.csv",
							"delimiter_name": ",",
							"row_as_header": true
						}
					}
				]
			},
			{
				"name": "bureau",
				"type": "Copy",
				"dependsOn": [],
				"policy": {
					"timeout": "0.12:00:00",
					"retry": 0,
					"retryIntervalInSeconds": 30,
					"secureOutput": false,
					"secureInput": false
				},
				"userProperties": [],
				"typeProperties": {
					"source": {
						"type": "PostgreSqlV2Source"
					},
					"sink": {
						"type": "DelimitedTextSink",
						"storeSettings": {
							"type": "AzureBlobFSWriteSettings"
						},
						"formatSettings": {
							"type": "DelimitedTextWriteSettings",
							"quoteAllText": true,
							"fileExtension": ".txt"
						}
					},
					"enableStaging": false,
					"translator": {
						"type": "TabularTranslator",
						"typeConversion": true,
						"typeConversionSettings": {
							"allowDataTruncation": true,
							"treatBooleanAsNumber": false
						}
					}
				},
				"inputs": [
					{
						"referenceName": "POSTGRE_loan_modeling",
						"type": "DatasetReference",
						"parameters": {
							"schema_name": "public",
							"table_name": "bureau"
						}
					}
				],
				"outputs": [
					{
						"referenceName": "CSV_ADLS_faza",
						"type": "DatasetReference",
						"parameters": {
							"container_name": "fazatest",
							"folder_name": "csv_ingestion/loan_modeling",
							"file_name": "bureau.csv",
							"delimiter_name": ",",
							"row_as_header": true
						}
					}
				]
			},
			{
				"name": "installment",
				"type": "Copy",
				"dependsOn": [],
				"policy": {
					"timeout": "0.12:00:00",
					"retry": 0,
					"retryIntervalInSeconds": 30,
					"secureOutput": false,
					"secureInput": false
				},
				"userProperties": [],
				"typeProperties": {
					"source": {
						"type": "PostgreSqlV2Source"
					},
					"sink": {
						"type": "DelimitedTextSink",
						"storeSettings": {
							"type": "AzureBlobFSWriteSettings"
						},
						"formatSettings": {
							"type": "DelimitedTextWriteSettings",
							"quoteAllText": true,
							"fileExtension": ".txt"
						}
					},
					"enableStaging": false,
					"translator": {
						"type": "TabularTranslator",
						"typeConversion": true,
						"typeConversionSettings": {
							"allowDataTruncation": true,
							"treatBooleanAsNumber": false
						}
					}
				},
				"inputs": [
					{
						"referenceName": "POSTGRE_loan_modeling",
						"type": "DatasetReference",
						"parameters": {
							"schema_name": "public",
							"table_name": "installment"
						}
					}
				],
				"outputs": [
					{
						"referenceName": "CSV_ADLS_faza",
						"type": "DatasetReference",
						"parameters": {
							"container_name": "fazatest",
							"folder_name": "csv_ingestion/loan_modeling",
							"file_name": "installment.csv",
							"delimiter_name": ",",
							"row_as_header": true
						}
					}
				]
			},
			{
				"name": "application_to_sql",
				"type": "Copy",
				"dependsOn": [
					{
						"activity": "application",
						"dependencyConditions": [
							"Succeeded"
						]
					}
				],
				"policy": {
					"timeout": "0.12:00:00",
					"retry": 0,
					"retryIntervalInSeconds": 30,
					"secureOutput": false,
					"secureInput": false
				},
				"userProperties": [],
				"typeProperties": {
					"source": {
						"type": "DelimitedTextSource",
						"storeSettings": {
							"type": "AzureBlobFSReadSettings",
							"recursive": true,
							"enablePartitionDiscovery": false
						},
						"formatSettings": {
							"type": "DelimitedTextReadSettings"
						}
					},
					"sink": {
						"type": "SqlServerSink",
						"writeBehavior": "insert",
						"sqlWriterUseTableLock": false
					},
					"enableStaging": false,
					"translator": {
						"type": "TabularTranslator",
						"typeConversion": true,
						"typeConversionSettings": {
							"allowDataTruncation": true,
							"treatBooleanAsNumber": false
						}
					}
				},
				"inputs": [
					{
						"referenceName": "CSV_ADLS_faza",
						"type": "DatasetReference",
						"parameters": {
							"container_name": "fazatest",
							"folder_name": "csv_ingestion/loan_modeling",
							"file_name": "application.csv",
							"delimiter_name": ",",
							"row_as_header": true
						}
					}
				],
				"outputs": [
					{
						"referenceName": "SQL_faza",
						"type": "DatasetReference",
						"parameters": {
							"schema_name": "dbo",
							"table_name": "application"
						}
					}
				]
			},
			{
				"name": "bureau_to_sql",
				"type": "Copy",
				"dependsOn": [
					{
						"activity": "bureau",
						"dependencyConditions": [
							"Succeeded"
						]
					}
				],
				"policy": {
					"timeout": "0.12:00:00",
					"retry": 0,
					"retryIntervalInSeconds": 30,
					"secureOutput": false,
					"secureInput": false
				},
				"userProperties": [],
				"typeProperties": {
					"source": {
						"type": "DelimitedTextSource",
						"storeSettings": {
							"type": "AzureBlobFSReadSettings",
							"recursive": true,
							"enablePartitionDiscovery": false
						},
						"formatSettings": {
							"type": "DelimitedTextReadSettings"
						}
					},
					"sink": {
						"type": "SqlServerSink",
						"writeBehavior": "insert",
						"sqlWriterUseTableLock": false
					},
					"enableStaging": false,
					"translator": {
						"type": "TabularTranslator",
						"typeConversion": true,
						"typeConversionSettings": {
							"allowDataTruncation": true,
							"treatBooleanAsNumber": false
						}
					}
				},
				"inputs": [
					{
						"referenceName": "CSV_ADLS_faza",
						"type": "DatasetReference",
						"parameters": {
							"container_name": "fazatest",
							"folder_name": "csv_ingestion/loan_modeling",
							"file_name": "bureau.csv",
							"delimiter_name": ",",
							"row_as_header": true
						}
					}
				],
				"outputs": [
					{
						"referenceName": "SQL_faza",
						"type": "DatasetReference",
						"parameters": {
							"schema_name": "dbo",
							"table_name": "bureau"
						}
					}
				]
			},
			{
				"name": "previous_application_to_sql",
				"type": "Copy",
				"dependsOn": [
					{
						"activity": "previous_application",
						"dependencyConditions": [
							"Succeeded"
						]
					}
				],
				"policy": {
					"timeout": "0.12:00:00",
					"retry": 0,
					"retryIntervalInSeconds": 30,
					"secureOutput": false,
					"secureInput": false
				},
				"userProperties": [],
				"typeProperties": {
					"source": {
						"type": "DelimitedTextSource",
						"storeSettings": {
							"type": "AzureBlobFSReadSettings",
							"recursive": true,
							"enablePartitionDiscovery": false
						},
						"formatSettings": {
							"type": "DelimitedTextReadSettings"
						}
					},
					"sink": {
						"type": "SqlServerSink",
						"writeBehavior": "insert",
						"sqlWriterUseTableLock": false
					},
					"enableStaging": false,
					"translator": {
						"type": "TabularTranslator",
						"typeConversion": true,
						"typeConversionSettings": {
							"allowDataTruncation": true,
							"treatBooleanAsNumber": false
						}
					}
				},
				"inputs": [
					{
						"referenceName": "CSV_ADLS_faza",
						"type": "DatasetReference",
						"parameters": {
							"container_name": "fazatest",
							"folder_name": "csv_ingestion/loan_modeling",
							"file_name": "previous_application.csv",
							"delimiter_name": ",",
							"row_as_header": true
						}
					}
				],
				"outputs": [
					{
						"referenceName": "SQL_faza",
						"type": "DatasetReference",
						"parameters": {
							"schema_name": "dbo",
							"table_name": "previous_application"
						}
					}
				]
			},
			{
				"name": "installment_to_sql",
				"type": "Copy",
				"dependsOn": [
					{
						"activity": "installment",
						"dependencyConditions": [
							"Succeeded"
						]
					}
				],
				"policy": {
					"timeout": "0.12:00:00",
					"retry": 0,
					"retryIntervalInSeconds": 30,
					"secureOutput": false,
					"secureInput": false
				},
				"userProperties": [],
				"typeProperties": {
					"source": {
						"type": "DelimitedTextSource",
						"storeSettings": {
							"type": "AzureBlobFSReadSettings",
							"recursive": true,
							"enablePartitionDiscovery": false
						},
						"formatSettings": {
							"type": "DelimitedTextReadSettings"
						}
					},
					"sink": {
						"type": "SqlServerSink",
						"writeBehavior": "insert",
						"sqlWriterUseTableLock": false
					},
					"enableStaging": false,
					"translator": {
						"type": "TabularTranslator",
						"typeConversion": true,
						"typeConversionSettings": {
							"allowDataTruncation": true,
							"treatBooleanAsNumber": false
						}
					}
				},
				"inputs": [
					{
						"referenceName": "CSV_ADLS_faza",
						"type": "DatasetReference",
						"parameters": {
							"container_name": "fazatest",
							"folder_name": "csv_ingestion/loan_modeling",
							"file_name": "installment.csv",
							"delimiter_name": ",",
							"row_as_header": true
						}
					}
				],
				"outputs": [
					{
						"referenceName": "SQL_faza",
						"type": "DatasetReference",
						"parameters": {
							"schema_name": "dbo",
							"table_name": "installment"
						}
					}
				]
			},
			{
				"name": "upsert_to_fact_loan_modeling",
				"type": "Copy",
				"dependsOn": [
					{
						"activity": "application_to_sql",
						"dependencyConditions": [
							"Succeeded"
						]
					},
					{
						"activity": "previous_application_to_sql",
						"dependencyConditions": [
							"Succeeded"
						]
					},
					{
						"activity": "bureau_to_sql",
						"dependencyConditions": [
							"Succeeded"
						]
					},
					{
						"activity": "installment_to_sql",
						"dependencyConditions": [
							"Succeeded"
						]
					}
				],
				"policy": {
					"timeout": "0.12:00:00",
					"retry": 0,
					"retryIntervalInSeconds": 30,
					"secureOutput": false,
					"secureInput": false
				},
				"userProperties": [],
				"typeProperties": {
					"source": {
						"type": "SqlServerSource",
						"sqlReaderQuery": "SELECT * FROM view_customer_loan_modeling",
						"queryTimeout": "02:00:00",
						"partitionOption": "None"
					},
					"sink": {
						"type": "SqlServerSink",
						"writeBehavior": "upsert",
						"upsertSettings": {
							"useTempDB": true,
							"keys": [
								"customer_no"
							]
						},
						"sqlWriterUseTableLock": false
					},
					"enableStaging": false,
					"translator": {
						"type": "TabularTranslator",
						"typeConversion": true,
						"typeConversionSettings": {
							"allowDataTruncation": true,
							"treatBooleanAsNumber": false
						}
					}
				},
				"inputs": [
					{
						"referenceName": "SQL_faza",
						"type": "DatasetReference",
						"parameters": {
							"schema_name": ".",
							"table_name": "."
						}
					}
				],
				"outputs": [
					{
						"referenceName": "SQL_faza",
						"type": "DatasetReference",
						"parameters": {
							"schema_name": "dbo",
							"table_name": "fact_loan_modeling"
						}
					}
				]
			}
		],
		"folder": {
			"name": "practice_case"
		},
		"annotations": []
	}
}